ariaclient/__init__.py
ariaclient/api.py
ariaclient/bot.py
ariaclient-4.0.15.dist-info/METADATA
ariaclient-4.0.15.dist-info/WHEEL
ariaclient-4.0.15.dist-info/top_level.txt
ariaclient-4.0.15.dist-info/RECORD
