Metadata-Version: 2.1
Name: ariaclient
Version: 4.0.15
Summary: Client side API and simple bot framekwork for fincloud-aria (version 4)
Home-page: https://github.com/fincloud-io/ariaclient
Author: Jon Jenkins
Author-email: jj@fincloud.io
Classifier: Programming Language :: Python :: 3
Classifier: License :: OSI Approved :: Apache Software License
Classifier: Operating System :: OS Independent
Requires-Python: >=3
